worldnews/__init__.py
worldnews/worldnews.py
worldnews-1.0.1.dist-info/DESCRIPTION.rst
worldnews-1.0.1.dist-info/METADATA
worldnews-1.0.1.dist-info/RECORD
worldnews-1.0.1.dist-info/WHEEL
worldnews-1.0.1.dist-info/metadata.json
worldnews-1.0.1.dist-info/top_level.txt
